pnw_python_subscriptions-1.1.3.dist-info/licenses/LICENSE.md
pnw_subscriptions/__init__.py
pnw_subscriptions/subscriptions.py
pnw_subscriptions/scripts/generic_listener.js
pnw_subscriptions/scripts/package.json
pnw_python_subscriptions-1.1.3.dist-info/METADATA
pnw_python_subscriptions-1.1.3.dist-info/WHEEL
pnw_python_subscriptions-1.1.3.dist-info/top_level.txt
pnw_python_subscriptions-1.1.3.dist-info/RECORD
