Metadata-Version: 2.4
Name: pnw-python-subscriptions
Version: 1.1.3
Summary: PNW subscription utility
Author: Sumnor
License: MIT
Requires-Python: >=3.7
License-File: LICENSE.md
Dynamic: license-file
